arxiv_bib_update.py
setup.py
arxiv_bib_update.egg-info/PKG-INFO
arxiv_bib_update.egg-info/SOURCES.txt
arxiv_bib_update.egg-info/dependency_links.txt
arxiv_bib_update.egg-info/entry_points.txt
arxiv_bib_update.egg-info/requires.txt
arxiv_bib_update.egg-info/top_level.txt