Metadata-Version: 1.0
Name: arxiv-bib-update
Version: 0.1.2
Summary: tool to search for and update out-of-date arXiv preprints in bibtex files
Home-page: http://github.com/nickhand/arxiv_bib_update
Author: Nick hand
Author-email: nicholas.adam.hand@gmail.com
License: UNKNOWN
Platform: UNKNOWN
